{
      "elicitation_inputs": {

                  "Person": [1, 2, 3, 4, 5, 6, 7, 8, 9, 10],
                  "Best guess": [0.1, 0.15, 0.15, 0.15, 0.18, 0.2, 0.2, 0.2, 0.25, 0.3],
                  "Best guess repeat": [0.1, 0.15, 0.15, 0.15, 0.18, 0.2, 0.2, 0.2, 0.25, 0.3],
                  "Min": [0.05, 0.05, 0.05, 0.05, 0.11, 0.05, 0.1, 0.13, 0.1, 0.05],
                  "Max": [0.2, 0.25, 0.25, 0.4, 0.25, 0.4, 0.4, 0.4, 0.4, 0.6]
      },

    "phit_inputs": {
          "boulder diameter": [0.2, 0.3, 0.4],
          "person diameter": [1, 1, 1],
          "square length": [30, 30, 30]
    }
}